certpwn/__init__.py
certpwn/version.py
certpwn/actions/__init__.py
certpwn/actions/basicaction.py
certpwn/actions/databaseaction.py
certpwn/actions/logaction.py
certpwn/actions/savefileaction.py
certpwn/actions/savejsonaction.py
certpwn/actions/syslogaction.py
certpwn/actions/telegramaction.py
certpwn/actions/twitteraction.py
certpwn/actions/webhookaction.py
certpwn/actions/tests/__init__.py
certpwn/actions/tests/basicaction_test.py
certpwn/actions/tests/savefileaction_test.py
certpwn/actions/tests/savejsonaction_test.py
certpwn/actions/tests/webhookaction_test.py
certpwn/analyzers/__init__.py
certpwn/analyzers/alwaystrueanalyzer.py
certpwn/analyzers/authoritykeyidanalyzer.py
certpwn/analyzers/basicanalyzer.py
certpwn/analyzers/caanalyzer.py
certpwn/analyzers/cafingerprintanalyzer.py
certpwn/analyzers/dnstwistanalyzer.py
certpwn/analyzers/domainregexanalyzer.py
certpwn/analyzers/fulldomainanalyzer.py
certpwn/analyzers/letsencryptanalyzer.py
certpwn/analyzers/precertanalyzer.py
certpwn/analyzers/regexdomainanalyzer.py
certpwn/analyzers/subdomainanalyzer.py
certpwn/analyzers/tldanalyzer.py
certpwn/analyzers/wildcardcertanalyzer.py
certpwn/analyzers/x509analyzer.py
certpwn/analyzers/tests/__init__.py
certpwn/analyzers/tests/alwaystrueanalyzer_test.py
certpwn/analyzers/tests/basicanalyzer_test.py
certpwn/analyzers/tests/cafingerprintanalyzer_test.py
certpwn/analyzers/tests/dnstwistanalyzer_test.py
certpwn/analyzers/tests/domainregexanalyzer_test.py
certpwn/analyzers/tests/fulldomainanalyzer_test.py
certpwn/analyzers/tests/mergedanalyzer_test.py
certpwn/analyzers/tests/precertanalyzer_test.py
certpwn/analyzers/tests/subdomainanalyzer_test.py
certpwn/analyzers/tests/wildcardcertanalyzer_test.py
certpwn/analyzers/tests/x509analyzer_test.py
certpwn/core/__init__.py
certpwn/core/actionhandler.py
certpwn/core/analyzerhandler.py
certpwn/core/certpwn.py
certpwn/core/certstreamwrapper.py
certpwn/core/certstreamdata/__init__.py
certpwn/core/certstreamdata/certstreamobject.py
certpwn-0.0.1rc0.dist-info/METADATA
certpwn-0.0.1rc0.dist-info/WHEEL
certpwn-0.0.1rc0.dist-info/top_level.txt
certpwn-0.0.1rc0.dist-info/RECORD
