Metadata-Version: 2.1
Name: certpwn
Version: 0.0.1rc0
Summary: Python framework for collecting and analyzing TLS certificate data via the Certificate Transparency Network
Home-page: https://github.com/d-Rickyy-b/certpwn
Author: d-Rickyy-b
Author-email: certpwn@rico-j.de
License: MIT
Keywords: python certificate tls osint framework
Platform: UNKNOWN
Classifier: Development Status :: 5 - Production/Stable
Classifier: Environment :: Console
Classifier: Intended Audience :: Developers
Classifier: Intended Audience :: Science/Research
Classifier: License :: OSI Approved :: MIT License
Classifier: Operating System :: OS Independent
Classifier: Topic :: Software Development :: Libraries :: Python Modules
Classifier: Topic :: Security
Classifier: Topic :: Internet
Classifier: Programming Language :: Python
Classifier: Programming Language :: Python :: 3.5
Classifier: Programming Language :: Python :: 3.6
Classifier: Programming Language :: Python :: 3.7
Requires-Dist: certstream (==1.11)
Requires-Dist: tldextract (==3.1.0)
Requires-Dist: dnstwist (==20201228)
Requires-Dist: requests (==2.25.1)
Requires-Dist: setuptools (==47.3.1)
